<?xml version="1.0" encoding="UTF-8"?>

<!-- generated on 2023-10-02 09:30:26 by Eclipse SUMO duarouter Version 1.12.0
<configuration xmlns:xsi="http://www.w3.org/2001/XMLSchema-instance" xsi:noNamespaceSchemaLocation="http://sumo.dlr.de/xsd/duarouterConfiguration.xsd">

    <input>
        <net-file value="turin.net.xml"/>
        <route-files value="turin.trips.xml"/>
    </input>

    <output>
        <output-file value="turin.trips.xml.tmp"/>
        <write-trips value="true"/>
    </output>

    <time>
        <begin value="0"/>
        <end value="600"/>
    </time>

    <report>
        <no-warnings value="true"/>
        <ignore-errors value="true"/>
        <no-step-log value="true"/>
    </report>

</configuration>
-->

<routes xmlns:xsi="http://www.w3.org/2001/XMLSchema-instance" xsi:noNamespaceSchemaLocation="http://sumo.dlr.de/xsd/routes_file.xsd">
    <trip id="0" depart="0.00" from="346319159" to="-1102649877#3"/>
    <trip id="1" depart="0.50" from="105600448#0" to="-8272429#0"/>
    <trip id="2" depart="1.00" from="397537027#4" to="37730532#9"/>
    <trip id="3" depart="1.50" from="714022408#0" to="-160667646#1"/>
    <trip id="4" depart="2.00" from="133855825#2" to="-1117205703#10"/>
    <trip id="5" depart="2.50" from="-727582095" to="191142224"/>
    <trip id="6" depart="3.00" from="-1123085977#1" to="-59712738#0"/>
    <trip id="7" depart="3.50" from="36843404#1" to="23182379#4"/>
    <trip id="8" depart="4.00" from="-756859271#0" to="28107362#14"/>
    <trip id="9" depart="4.50" from="502438902#2" to="-104675798#1"/>
    <trip id="10" depart="5.00" from="49304544" to="38027665#1"/>
    <trip id="11" depart="5.50" from="111995476#1" to="-38027983#11"/>
    <trip id="12" depart="6.00" from="862454065#1" to="1148433532"/>
    <trip id="13" depart="6.50" from="-190985111#2" to="-191108737#0"/>
    <trip id="14" depart="7.00" from="584766945#0" to="302520057#4"/>
    <trip id="15" depart="7.50" from="49723042#4" to="405055927#2"/>
    <trip id="16" depart="8.00" from="220847826#4" to="881245057#0"/>
    <trip id="17" depart="8.50" from="121952553#6" to="23575327#1"/>
    <trip id="18" depart="9.00" from="572328742#2" to="328929617#2"/>
    <trip id="19" depart="9.50" from="607397487#0" to="26620384#0"/>
    <trip id="20" depart="10.00" from="37886525" to="-121952583#4"/>
    <trip id="21" depart="10.50" from="-814585369" to="110904634#0"/>
    <trip id="22" depart="11.00" from="-160591231#6" to="-882052276"/>
    <trip id="23" depart="11.50" from="-22897942#2" to="1095217615#8"/>
    <trip id="24" depart="12.00" from="332306557#0" to="125665634#0"/>
    <trip id="25" depart="12.50" from="1170352353#0" to="-727584876#2"/>
    <trip id="26" depart="13.00" from="103504284#0" to="824542215#11"/>
    <trip id="27" depart="13.50" from="36812654#20" to="316018812#1"/>
    <trip id="28" depart="14.00" from="-43569688#2" to="40196945#1"/>
    <trip id="29" depart="14.50" from="-40735733#2" to="130443635#6"/>
    <trip id="30" depart="15.00" from="926732503#0" to="36916539#4"/>
    <trip id="31" depart="15.50" from="23088940#3" to="37837426#2"/>
    <trip id="32" depart="16.00" from="573860847#12" to="48056814#2"/>
    <trip id="33" depart="16.50" from="-816120700" to="-1118317793"/>
    <trip id="34" depart="17.00" from="111238558#1" to="107426175#0"/>
    <trip id="35" depart="17.50" from="-681328860" to="83051447#2"/>
    <trip id="36" depart="18.00" from="659342824#0" to="111859690#1"/>
    <trip id="37" depart="18.50" from="36916541#20" to="133198392#2"/>
    <trip id="38" depart="19.00" from="77914306#0" to="151212521#1"/>
    <trip id="39" depart="19.50" from="1027290198" to="102597012#6"/>
    <trip id="40" depart="20.00" from="23182366#2" to="106904855#0"/>
    <trip id="41" depart="20.50" from="257171430#0" to="757059572#1"/>
    <trip id="42" depart="21.00" from="130443635#2" to="-81632518#4"/>
    <trip id="43" depart="21.50" from="966696334#1" to="192999988#1"/>
    <trip id="45" depart="22.50" from="-243278285#0" to="359380195#5"/>
    <trip id="46" depart="23.00" from="48063707#11" to="134690526#3"/>
    <trip id="47" depart="23.50" from="-135860932#7" to="130443653#9"/>
    <trip id="48" depart="24.00" from="966240518" to="22956026#5"/>
    <trip id="49" depart="24.50" from="87988937#3" to="651764272#9"/>
    <trip id="50" depart="25.00" from="-107309874#1" to="39773187#1"/>
    <trip id="51" depart="25.50" from="375045488#11" to="23034861#3"/>
    <trip id="52" depart="26.00" from="1034770922#1" to="36916541#29"/>
    <trip id="53" depart="26.50" from="-252731823" to="144874012#0"/>
    <trip id="54" depart="27.00" from="139118802#0" to="85426929#4"/>
    <trip id="55" depart="27.50" from="657572430#2" to="106904875#0"/>
    <trip id="56" depart="28.00" from="165339488#2" to="-463853185#1"/>
    <trip id="57" depart="28.50" from="77077234#0" to="667827203#5"/>
    <trip id="58" depart="29.00" from="108646527#1" to="368807876#7"/>
    <trip id="59" depart="29.50" from="28681137#4" to="-38027102#0"/>
    <trip id="60" depart="30.00" from="426578845#3" to="230847356#0"/>
    <trip id="61" depart="30.50" from="44104490#0" to="22981924#0"/>
    <trip id="62" depart="31.00" from="-101332765#5" to="112610109#6"/>
    <trip id="63" depart="31.50" from="-111514164#2" to="816737047"/>
    <trip id="64" depart="32.00" from="661301147#0" to="580542103#1"/>
    <trip id="66" depart="33.00" from="660113175#0" to="83640998#4"/>
    <trip id="67" depart="33.50" from="-173047160" to="170397675#2"/>
    <trip id="68" depart="34.00" from="-149146789#11" to="43976571"/>
    <trip id="69" depart="34.50" from="43012021#1" to="-306423366#0"/>
    <trip id="70" depart="35.00" from="149822407" to="23463796#4"/>
    <trip id="71" depart="35.50" from="1028424336" to="674865542#2"/>
    <trip id="72" depart="36.00" from="133868162#3" to="-756569653#8"/>
    <trip id="73" depart="36.50" from="22885727" to="405055927#7"/>
    <trip id="74" depart="37.00" from="-59712738#1" to="111801806#0"/>
    <trip id="75" depart="37.50" from="96351501#0" to="371630999#6"/>
    <trip id="76" depart="38.00" from="134460803#0" to="220847817#2"/>
    <trip id="77" depart="38.50" from="-286598317#0" to="-83808970#0"/>
    <trip id="78" depart="39.00" from="111981877#0" to="28106934#2"/>
    <trip id="79" depart="39.50" from="-816212416" to="-819766946#1"/>
    <trip id="80" depart="40.00" from="-149819227#3" to="363701247#0"/>
    <trip id="81" depart="40.50" from="-816120700" to="767390779#7"/>
    <trip id="82" depart="41.00" from="60131972#3" to="-145958290#1"/>
    <trip id="83" depart="41.50" from="-8272429#0" to="37640545#7"/>
    <trip id="84" depart="42.00" from="-685440556" to="-327999345"/>
    <trip id="85" depart="42.50" from="81892451" to="257357068#3"/>
    <trip id="86" depart="43.00" from="149425931#0" to="486933215"/>
    <trip id="87" depart="43.50" from="49723092#2" to="-572748508#5"/>
    <trip id="88" depart="44.00" from="-200750063" to="135860932#5"/>
    <trip id="89" depart="44.50" from="133868177#3" to="154716226#11"/>
    <trip id="90" depart="45.00" from="38323010#1" to="37679702#3"/>
    <trip id="91" depart="45.50" from="900740107#1" to="-192659132#0"/>
    <trip id="92" depart="46.00" from="130443660#0" to="1149694682#0"/>
    <trip id="93" depart="46.50" from="607393606#2" to="103428634#1"/>
    <trip id="94" depart="47.00" from="-563843021#0" to="149190770#1"/>
    <trip id="95" depart="47.50" from="133855825#1" to="1095462865"/>
    <trip id="96" depart="48.00" from="-893901258#1" to="81355072#4"/>
    <trip id="97" depart="48.50" from="134690548#0" to="655554539"/>
    <trip id="98" depart="49.00" from="23026016#2" to="-130443630#16"/>
    <trip id="99" depart="49.50" from="996232952#1" to="586896066#1"/>
    <trip id="100" depart="50.00" from="876131440" to="81563077#9"/>
    <trip id="101" depart="50.50" from="58759055#1" to="-400406089#2"/>
    <trip id="102" depart="51.00" from="154716209#4" to="-765543785#0"/>
    <trip id="103" depart="51.50" from="130443651#0" to="-133661501#6"/>
    <trip id="104" depart="52.00" from="121952558#5" to="900926804#2"/>
    <trip id="105" depart="52.50" from="1028424336" to="486666533#17"/>
    <trip id="106" depart="53.00" from="145954704#3" to="134690556#1"/>
    <trip id="107" depart="53.50" from="862454067#0" to="96351497#0"/>
    <trip id="108" depart="54.00" from="23066443#5" to="39685722#0"/>
    <trip id="109" depart="54.50" from="-38314397#1" to="111262067#5"/>
    <trip id="110" depart="55.00" from="876131437#1" to="26982330#6"/>
    <trip id="111" depart="55.50" from="22907738#11" to="42737802#2"/>
    <trip id="112" depart="56.00" from="-134460774#11" to="27782011#5"/>
    <trip id="113" depart="56.50" from="166727313#0" to="621959187#1"/>
    <trip id="114" depart="57.00" from="-397537026" to="873160686#0"/>
    <trip id="115" depart="57.50" from="-160591234#4" to="-552708120#1"/>
    <trip id="116" depart="58.00" from="26982395#6" to="37715948#1"/>
    <trip id="117" depart="58.50" from="-82290357#0" to="-257171432#0"/>
    <trip id="118" depart="59.00" from="69931595#2" to="1023658748#0"/>
    <trip id="119" depart="59.50" from="26982330#3" to="330713238#1"/>
    <trip id="120" depart="60.00" from="133661501#4" to="27781952#1"/>
    <trip id="121" depart="60.50" from="191228010" to="82207182"/>
    <trip id="122" depart="61.00" from="-621959187#1" to="395600340#2"/>
    <trip id="123" depart="61.50" from="-829883366" to="133198392#5"/>
    <trip id="124" depart="62.00" from="37290625#19" to="111514165#0"/>
    <trip id="125" depart="62.50" from="111238565#0" to="43140496#1"/>
    <trip id="126" depart="63.00" from="-149822413#1" to="151167659#0"/>
    <trip id="127" depart="63.50" from="992676612" to="966122021#1"/>
    <trip id="128" depart="64.00" from="-151167655#2" to="-762457085#1"/>
    <trip id="129" depart="64.50" from="1028424336" to="819816251"/>
    <trip id="130" depart="65.00" from="667668276#2" to="685215224"/>
    <trip id="131" depart="65.50" from="116820397#4" to="-38103321"/>
    <trip id="132" depart="66.00" from="572744532#1" to="38081511#0"/>
    <trip id="133" depart="66.50" from="290005765#1" to="914557939#1"/>
    <trip id="134" depart="67.00" from="36903944#12" to="-1055422268#3"/>
    <trip id="135" depart="67.50" from="551896092#15" to="111504831#6"/>
    <trip id="137" depart="68.50" from="-36875183#2" to="-243276783#1"/>
    <trip id="138" depart="69.00" from="-23490358#1" to="237436107#1"/>
    <trip id="139" depart="69.50" from="1055410289#0" to="302763280#1"/>
    <trip id="140" depart="70.00" from="38081496#0" to="-657572430#4"/>
    <trip id="141" depart="70.50" from="329301856#3" to="107166846#3"/>
    <trip id="142" depart="71.00" from="154844465#2" to="767390779#3"/>
    <trip id="143" depart="71.50" from="58413962#3" to="-173992155#0"/>
    <trip id="144" depart="72.00" from="133868177#3" to="1094437534#3"/>
    <trip id="145" depart="72.50" from="-104148308#0" to="463853185#1"/>
    <trip id="146" depart="73.00" from="332861395#0" to="106836308#4"/>
    <trip id="147" depart="73.50" from="39977260#4" to="23575175#2"/>
    <trip id="148" depart="74.00" from="134009740#6" to="-105601667#0"/>
    <trip id="149" depart="74.50" from="-154716204#0" to="690999415#1"/>
    <trip id="150" depart="75.00" from="757059565#2" to="23182423#4"/>
    <trip id="151" depart="75.50" from="572744559#1" to="27781803#3"/>
    <trip id="152" depart="76.00" from="-37973566#6" to="-292960610#0"/>
    <trip id="153" depart="76.50" from="110678682#10" to="757534983#0"/>
    <trip id="154" depart="77.00" from="481884819#8" to="651764272#8"/>
    <trip id="155" depart="77.50" from="748671327#1" to="-740993627#0"/>
    <trip id="156" depart="78.00" from="-893901258#0" to="-207858426"/>
    <trip id="157" depart="78.50" from="44468712#19" to="697584770#3"/>
    <trip id="158" depart="79.00" from="132316384#2" to="332306557#2"/>
    <trip id="159" depart="79.50" from="-38306581#4" to="816876620"/>
    <trip id="160" depart="80.00" from="62094934#1" to="881916064#5"/>
    <trip id="161" depart="80.50" from="50339443#1" to="685440567"/>
    <trip id="162" depart="81.00" from="-111981879#0" to="40760631#1"/>
    <trip id="163" depart="81.50" from="111801783" to="81792644"/>
    <trip id="164" depart="82.00" from="48978999#0" to="657572429#3"/>
    <trip id="165" depart="82.50" from="50339443#1" to="107426161#3"/>
    <trip id="166" depart="83.00" from="463853185#4" to="-22898291#1"/>
    <trip id="167" depart="83.50" from="651764271#1" to="646315031#1"/>
    <trip id="168" depart="84.00" from="-765105682#0" to="572328742#2"/>
    <trip id="169" depart="84.50" from="149023979#1" to="1116516509#1"/>
    <trip id="170" depart="85.00" from="481545836" to="-85978184#0"/>
    <trip id="171" depart="85.50" from="-1118326501" to="-584766946"/>
    <trip id="172" depart="86.00" from="111702082#1" to="657572430#2"/>
    <trip id="173" depart="86.50" from="875446016#1" to="1097325369"/>
    <trip id="174" depart="87.00" from="359380195#3" to="133615149"/>
    <trip id="175" depart="87.50" from="893901266" to="23028464#6"/>
    <trip id="176" depart="88.00" from="824542215#19" to="-243270141#1"/>
    <trip id="177" depart="88.50" from="87776950#0" to="-459789841#1"/>
    <trip id="178" depart="89.00" from="873283811#7" to="107425018#1"/>
    <trip id="179" depart="89.50" from="-237436107#2" to="141433459"/>
    <trip id="180" depart="90.00" from="38320044#4-AddedOnRampEdge" to="111859620#1"/>
    <trip id="181" depart="90.50" from="28193008#0" to="194336585#1"/>
    <trip id="182" depart="91.00" from="125665635#4" to="26540081#11"/>
    <trip id="183" depart="91.50" from="-95514276#1" to="38306581#7"/>
    <trip id="184" depart="92.00" from="-1023658749" to="81563075#1"/>
    <trip id="185" depart="92.50" from="22876733#0" to="397430748#0"/>
    <trip id="186" depart="93.00" from="39977267#2" to="376503487#2"/>
    <trip id="187" depart="93.50" from="1160179613#5" to="-139070454#7"/>
    <trip id="188" depart="94.00" from="37139965#1" to="112950876"/>
    <trip id="189" depart="94.50" from="110904688#1" to="60131972#1"/>
    <trip id="190" depart="95.00" from="38081517#1" to="1115285030"/>
    <trip id="191" depart="95.50" from="110801308#6" to="134119964#0"/>
    <trip id="192" depart="96.00" from="130443659#5" to="1112476318#2"/>
    <trip id="193" depart="96.50" from="-330720250" to="134640686#2"/>
    <trip id="195" depart="97.50" from="756859271#0" to="323978916#3"/>
    <trip id="196" depart="98.00" from="1095217615#7" to="23313517#7"/>
    <trip id="197" depart="98.50" from="-101186594" to="110801311#3"/>
    <trip id="198" depart="99.00" from="134124998#0" to="272236474#0"/>
    <trip id="199" depart="99.50" from="36916539#1" to="154716208#0"/>
    <trip id="200" depart="100.00" from="134640700#6" to="-765543783#5"/>
    <trip id="201" depart="100.50" from="149449754#5" to="758105911"/>
    <trip id="202" depart="101.00" from="481884819#6" to="-40870794#1"/>
    <trip id="203" depart="101.50" from="-172498376" to="208420935"/>
    <trip id="204" depart="102.00" from="326284077" to="1137802675#0"/>
    <trip id="205" depart="102.50" from="552361913#7" to="43018568#2"/>
    <trip id="206" depart="103.00" from="37305404#0" to="-83808966#1"/>
    <trip id="207" depart="103.50" from="-58780682#6" to="-1096795080#0"/>
    <trip id="208" depart="104.00" from="-8668802#2" to="158526051#4"/>
    <trip id="209" depart="104.50" from="58768055#25" to="-148961543"/>
    <trip id="210" depart="105.00" from="133198392#3" to="36357298#1"/>
    <trip id="211" depart="105.50" from="-58414208#6" to="37981428#2"/>
    <trip id="212" depart="106.00" from="159296195#0" to="1016808077"/>
    <trip id="213" depart="106.50" from="36916541#35" to="-104230903#0"/>
    <trip id="214" depart="107.00" from="40745994#0" to="457425214#5"/>
    <trip id="215" depart="107.50" from="-23463862" to="134898666#1"/>
    <trip id="216" depart="108.00" from="-452931327#10" to="863937087#17"/>
    <trip id="218" depart="109.00" from="-889379656" to="60131978#0"/>
    <trip id="219" depart="109.50" from="148591954" to="533837088#4"/>
    <trip id="220" depart="110.00" from="37228341#1" to="921849958#2"/>
    <trip id="221" depart="110.50" from="272236474#1" to="83710621"/>
    <trip id="222" depart="111.00" from="713797729" to="31860136#6"/>
    <trip id="223" depart="111.50" from="38081510#2" to="190658505#2"/>
    <trip id="224" depart="112.00" from="572714688#1" to="23313517#5"/>
    <trip id="225" depart="112.50" from="745220416#1" to="41900657#1"/>
    <trip id="226" depart="113.00" from="149819238#0" to="106568053#2"/>
    <trip id="227" depart="113.50" from="-880575679#0" to="36876578#8"/>
    <trip id="228" depart="114.00" from="42979511" to="22876730#0"/>
    <trip id="229" depart="114.50" from="31860136#0" to="108646518#3"/>
    <trip id="230" depart="115.00" from="-154889905#1" to="1107782312"/>
    <trip id="231" depart="115.50" from="105308013#1" to="112174722#2"/>
    <trip id="232" depart="116.00" from="22897740#6" to="-36857683#3"/>
    <trip id="233" depart="116.50" from="-816876620" to="37973571#0"/>
    <trip id="234" depart="117.00" from="37908666#10" to="-134572344#1"/>
    <trip id="235" depart="117.50" from="132319217" to="23124243#8"/>
    <trip id="236" depart="118.00" from="133259885#4" to="-678628384#6"/>
    <trip id="237" depart="118.50" from="133849457#5" to="765642597"/>
    <trip id="238" depart="119.00" from="257171425#5" to="37973572#7"/>
    <trip id="239" depart="119.50" from="59618373#3" to="447699318#4"/>
    <trip id="240" depart="120.00" from="121952583#6" to="-104390538#0"/>
    <trip id="241" depart="120.50" from="112950832#0" to="43273620#6"/>
    <trip id="243" depart="121.50" from="133661501#0" to="426578845#5"/>
    <trip id="244" depart="122.00" from="22956026#2" to="302426937#1"/>
    <trip id="245" depart="122.50" from="-757053235#0" to="-81792553#0"/>
    <trip id="246" depart="123.00" from="134420437#6" to="-111604743#0"/>
    <trip id="247" depart="123.50" from="1118326501" to="37761132#1"/>
    <trip id="248" depart="124.00" from="131645490#4" to="-39977263#1"/>
    <trip id="249" depart="124.50" from="149146783#8" to="-29495014#0"/>
    <trip id="250" depart="125.00" from="312270947#0" to="-110904606#4"/>
    <trip id="251" depart="125.50" from="128039757" to="25568829#1"/>
    <trip id="252" depart="126.00" from="-112568282#21" to="36932294#0"/>
    <trip id="253" depart="126.50" from="-36934168" to="154484171#4"/>
    <trip id="254" depart="127.00" from="-132319228" to="130443630#7"/>
    <trip id="255" depart="127.50" from="-681848896" to="112610160#3"/>
    <trip id="256" depart="128.00" from="424269158#4" to="130443630#9"/>
    <trip id="257" depart="128.50" from="40760618#5" to="580542103#8"/>
    <trip id="258" depart="129.00" from="-914405033" to="-154716196#8"/>
    <trip id="259" depart="129.50" from="-111504826#2" to="230847356#1"/>
    <trip id="260" depart="130.00" from="99754717#1" to="1174493054#3"/>
    <trip id="261" depart="130.50" from="36857139#1" to="481814154"/>
    <trip id="262" depart="131.00" from="36876577#10" to="435787896#0"/>
    <trip id="263" depart="131.50" from="83710623" to="-60131785#0"/>
    <trip id="264" depart="132.00" from="-111596216#4" to="-37973566#6"/>
    <trip id="265" depart="132.50" from="-328929610#1" to="37640546#7"/>
    <trip id="266" depart="133.00" from="23262202#3" to="-80877381#8"/>
    <trip id="267" depart="133.50" from="37830679#1" to="450664579"/>
    <trip id="268" depart="134.00" from="-41900657#1" to="309843440#3"/>
    <trip id="269" depart="134.50" from="40735732#2" to="-23800991#1"/>
    <trip id="270" depart="135.00" from="552708119#5" to="875445772#0"/>
    <trip id="271" depart="135.50" from="-23683989#4" to="-110678664#11"/>
    <trip id="272" depart="136.00" from="110904629#0" to="37738036#8"/>
    <trip id="273" depart="136.50" from="863937087#9" to="133259881#1"/>
    <trip id="274" depart="137.00" from="38027668#7" to="-149190777#4"/>
    <trip id="275" depart="137.50" from="37709787#1" to="359380194#1"/>
    <trip id="276" depart="138.00" from="-22932504" to="469372935#0"/>
    <trip id="277" depart="138.50" from="58770725#0" to="294507534#4"/>
    <trip id="278" depart="139.00" from="-286598317#2" to="894727042#0"/>
    <trip id="279" depart="139.50" from="447701120#8" to="116820389#2"/>
    <trip id="280" depart="140.00" from="134124979#5" to="127949012#1"/>
    <trip id="281" depart="140.50" from="170563870" to="1158706537#2"/>
    <trip id="282" depart="141.00" from="58768055#21" to="572744581#1"/>
    <trip id="283" depart="141.50" from="-23262356#1" to="873160686#0"/>
    <trip id="284" depart="142.00" from="332306556#0" to="572748523#7"/>
    <trip id="285" depart="142.50" from="37942667#3" to="145954707#13"/>
    <trip id="286" depart="143.00" from="39671245#0" to="875445775#0"/>
    <trip id="287" depart="143.50" from="1046756042#0" to="558288366#2"/>
    <trip id="288" depart="144.00" from="22876729#0" to="166605395#1"/>
    <trip id="289" depart="144.50" from="134420437#18" to="405900733#4"/>
    <trip id="290" depart="145.00" from="103851605" to="61293132#0"/>
    <trip id="291" depart="145.50" from="572714689#2" to="-160600494#1"/>
    <trip id="292" depart="146.00" from="667827203#11" to="1015878042#2"/>
    <trip id="293" depart="146.50" from="149116234#3" to="31652636#1"/>
    <trip id="294" depart="147.00" from="121952560#0" to="-111596216#6"/>
    <trip id="295" depart="147.50" from="58777841#2" to="-48801898#0"/>
    <trip id="296" depart="148.00" from="-681848897" to="50339443#4"/>
    <trip id="297" depart="148.50" from="111995476#3" to="685440558"/>
    <trip id="298" depart="149.00" from="37837434#0" to="1090748961"/>
    <trip id="299" depart="149.50" from="-106904879#1" to="83709549#15"/>
    <trip id="300" depart="150.00" from="-173047160" to="397430750#10"/>
    <trip id="301" depart="150.50" from="154844465#3" to="43836954#5"/>
    <trip id="302" depart="151.00" from="37709787#1" to="370092974#1"/>
    <trip id="303" depart="151.50" from="154986394#10" to="49578366#2"/>
    <trip id="304" depart="152.00" from="-191381259" to="-82225016#1"/>
    <trip id="305" depart="152.50" from="37725936#0" to="111702090#1"/>
    <trip id="306" depart="153.00" from="25568840#0" to="157367526#3"/>
    <trip id="307" depart="153.50" from="207858427#0" to="135016488#4"/>
    <trip id="308" depart="154.00" from="40271562#4" to="1130879897#1"/>
    <trip id="309" depart="154.50" from="37856845#0" to="108329426#2"/>
    <trip id="311" depart="155.50" from="-58233300#3" to="-257171429#2"/>
    <trip id="312" depart="156.00" from="220847824#3" to="44104491#1"/>
    <trip id="313" depart="156.50" from="-543492893#0" to="-801907518"/>
    <trip id="314" depart="157.00" from="154716197#1" to="39977260#0"/>
    <trip id="315" depart="157.50" from="881916066#5" to="22906913#4"/>
    <trip id="316" depart="158.00" from="106581160#0" to="-207854783#0"/>
    <trip id="317" depart="158.50" from="-58414208#2" to="-858064349#3"/>
    <trip id="318" depart="159.00" from="-481228653" to="-106568791#0"/>
    <trip id="319" depart="159.50" from="217850378" to="108637182#0"/>
    <trip id="320" depart="160.00" from="881905842#2" to="237436107#6"/>
    <trip id="321" depart="160.50" from="37771903#1" to="-286598317#0"/>
    <trip id="322" depart="161.00" from="636566937#5" to="172409588#1"/>
    <trip id="323" depart="161.50" from="652758223" to="257685415#0"/>
    <trip id="324" depart="162.00" from="149190770#2" to="149116215"/>
    <trip id="325" depart="162.50" from="-524463976#11" to="-130443657"/>
    <trip id="326" depart="163.00" from="8272313#8" to="160587552#1"/>
    <trip id="327" depart="163.50" from="559747870#1" to="133849456#1"/>
    <trip id="328" depart="164.00" from="-154409621#0" to="36334751#4"/>
    <trip id="329" depart="164.50" from="-133661501#3" to="-37830678#1"/>
    <trip id="330" depart="165.00" from="23182640#4" to="111604747"/>
    <trip id="331" depart="165.50" from="956017698#0" to="-256370023#0"/>
    <trip id="333" depart="166.50" from="48056807#1" to="-839327616#5"/>
    <trip id="334" depart="167.00" from="191213703" to="149402452"/>
    <trip id="335" depart="167.50" from="134690536#0" to="6502123#8"/>
    <trip id="336" depart="168.00" from="929173037#0" to="1116516510#1"/>
    <trip id="337" depart="168.50" from="306766279#0" to="316299338#12"/>
    <trip id="338" depart="169.00" from="39971283#6" to="83676860#3"/>
    <trip id="339" depart="169.50" from="-661251715" to="-755147086#9"/>
    <trip id="340" depart="170.00" from="369518908#1" to="-38081508#1"/>
    <trip id="341" depart="170.50" from="-43907780#2" to="-149146787#10"/>
    <trip id="342" depart="171.00" from="-103428639#0" to="149394531"/>
    <trip id="343" depart="171.50" from="26982286#1" to="110904688#2"/>
    <trip id="344" depart="172.00" from="-816876620" to="38228091#3"/>
    <trip id="345" depart="172.50" from="37856846#2" to="149819239#1"/>
    <trip id="346" depart="173.00" from="37679195#1" to="81400143#0"/>
    <trip id="347" depart="173.50" from="466900337#2" to="353164584"/>
    <trip id="348" depart="174.00" from="37041493#2" to="82091200"/>
    <trip id="349" depart="174.50" from="133868191#3" to="23182366#2"/>
    <trip id="350" depart="175.00" from="36812654#11" to="779031154#4"/>
    <trip id="351" depart="175.50" from="56244273#1" to="-148961532"/>
    <trip id="352" depart="176.00" from="-41238895" to="1117123169#3"/>
    <trip id="353" depart="176.50" from="40735736#1" to="257171431#0"/>
    <trip id="354" depart="177.00" from="107289450#1" to="-265600014#2"/>
    <trip id="355" depart="177.50" from="37679200#21" to="38027671#2"/>
    <trip id="356" depart="178.00" from="828546476#0" to="185594231#4"/>
    <trip id="357" depart="178.50" from="158526051#2" to="-152825882#1"/>
    <trip id="358" depart="179.00" from="-122258528#4" to="138713421#0"/>
    <trip id="359" depart="179.50" from="111514164#3" to="104148308#1"/>
    <trip id="360" depart="180.00" from="-186760727#0" to="873283812#0"/>
    <trip id="361" depart="180.50" from="572744594#2" to="26293224#1"/>
    <trip id="362" depart="181.00" from="839130025#1" to="996232968#5"/>
    <trip id="363" depart="181.50" from="37290628#0" to="107539769#3"/>
    <trip id="364" depart="182.00" from="-122368887" to="43684742#6"/>
    <trip id="365" depart="182.50" from="149230224#0" to="372173607"/>
    <trip id="366" depart="183.00" from="79606555#6" to="-48765724#1"/>
    <trip id="367" depart="183.50" from="257171438" to="36838612#1"/>
    <trip id="368" depart="184.00" from="154986395#0" to="-171930548"/>
    <trip id="369" depart="184.50" from="112610139#0" to="1136460102#2"/>
    <trip id="370" depart="185.00" from="37278469#1" to="646280627#1"/>
    <trip id="371" depart="185.50" from="1117123169#6" to="37973568#2"/>
    <trip id="372" depart="186.00" from="1072454155" to="833993643#0"/>
    <trip id="373" depart="186.50" from="531477507#0" to="23463811#0"/>
    <trip id="374" depart="187.00" from="144874012#0" to="111859690#1"/>
    <trip id="375" depart="187.50" from="111549921#0" to="877851359#0"/>
    <trip id="376" depart="188.00" from="131645490#0" to="207858126#1"/>
    <trip id="377" depart="188.50" from="925606978#0" to="37351086#2"/>
    <trip id="378" depart="189.00" from="22907751#0" to="134417910#4"/>
    <trip id="379" depart="189.50" from="-56015537#2" to="122368885#5"/>
    <trip id="380" depart="190.00" from="41245532#5" to="35469324#1"/>
    <trip id="381" depart="190.50" from="421109897#6" to="-657572430#3"/>
    <trip id="382" depart="191.00" from="23018163#2" to="816157290#1"/>
    <trip id="383" depart="191.50" from="134460803#1" to="38027665#11"/>
    <trip id="384" depart="192.00" from="-287540612" to="881245057#1"/>
    <trip id="385" depart="192.50" from="28681137#2" to="-956017698#1"/>
    <trip id="386" depart="193.00" from="-39831540#3" to="23490292#4"/>
    <trip id="387" depart="193.50" from="23027995#11" to="-182851488"/>
    <trip id="388" depart="194.00" from="946456581#1" to="80347021#4"/>
    <trip id="389" depart="194.50" from="149116217#3" to="-251612439"/>
    <trip id="390" depart="195.00" from="572740880" to="185581486#3"/>
    <trip id="391" depart="195.50" from="38027983#6" to="192219877#1"/>
    <trip id="392" depart="196.00" from="1055733688#0" to="58414208#6"/>
    <trip id="393" depart="196.50" from="890119492#0" to="1015878042#0"/>
    <trip id="394" depart="197.00" from="23027965#1" to="130443665#9"/>
    <trip id="395" depart="197.50" from="80869692#1" to="192217483#1"/>
    <trip id="396" depart="198.00" from="666249836#4" to="657572429#1"/>
    <trip id="397" depart="198.50" from="105602698" to="49001120#2"/>
    <trip id="398" depart="199.00" from="133203518#2" to="82207172#1"/>
    <trip id="399" depart="199.50" from="170590356#3" to="572744499#2"/>
    <trip id="400" depart="200.00" from="106581160#0" to="111504820#3"/>
    <trip id="401" depart="200.50" from="257357078#0" to="992676613#2"/>
    <trip id="402" depart="201.00" from="154881339#0" to="-37730532#6"/>
    <trip id="403" depart="201.50" from="22876733#2" to="116810536#0"/>
    <trip id="404" depart="202.00" from="23027994#5" to="23182332#1"/>
    <trip id="405" depart="202.50" from="145954707#0" to="112568304#4"/>
    <trip id="406" depart="203.00" from="-561528801" to="38027102#8"/>
    <trip id="407" depart="203.50" from="240482838#4" to="-890222451#0"/>
    <trip id="408" depart="204.00" from="439021002#0" to="-1177239717#0"/>
    <trip id="409" depart="204.50" from="40029751#1" to="38103345#4"/>
    <trip id="410" depart="205.00" from="50624777#1" to="132316382#6"/>
    <trip id="411" depart="205.50" from="37138416#4" to="572744517#0"/>
    <trip id="412" depart="206.00" from="890222451#2" to="179917799#4"/>
    <trip id="413" depart="206.50" from="-1186075027" to="186760727#2"/>
    <trip id="414" depart="207.00" from="26293224#14" to="667732741#0"/>
    <trip id="415" depart="207.50" from="657572415#10" to="149024030"/>
    <trip id="416" depart="208.00" from="193440715#0" to="149864370#0"/>
    <trip id="417" depart="208.50" from="38118392#1" to="134124995#0"/>
    <trip id="418" depart="209.00" from="36916539#4" to="-38027668#6"/>
    <trip id="419" depart="209.50" from="149190771#1" to="876531530#0"/>
    <trip id="420" depart="210.00" from="111981883#0" to="379511956#9"/>
    <trip id="421" depart="210.50" from="36843404#0" to="61293337"/>
    <trip id="422" depart="211.00" from="58779937#4" to="649706887#1"/>
    <trip id="423" depart="211.50" from="121952575" to="111995448#6"/>
    <trip id="425" depart="212.50" from="651764272#3" to="-112568282#2"/>
    <trip id="426" depart="213.00" from="-149146783#18" to="363701247#1"/>
    <trip id="427" depart="213.50" from="80716819#0" to="966696322#0"/>
    <trip id="428" depart="214.00" from="405900728" to="140264718#2"/>
    <trip id="429" depart="214.50" from="-207858429#1" to="36812654#24"/>
    <trip id="430" depart="215.00" from="651764272#8" to="149116231#2"/>
    <trip id="431" depart="215.50" from="37761128#2" to="764003829#0"/>
    <trip id="432" depart="216.00" from="-130443659#2" to="50168888#4"/>
    <trip id="433" depart="216.50" from="107539772#0" to="129099206#4"/>
    <trip id="434" depart="217.00" from="-37837444#2" to="23015884#0"/>
    <trip id="435" depart="217.50" from="234419734#0" to="494263440#1"/>
    <trip id="436" depart="218.00" from="-43140430#2" to="-149822412#1"/>
    <trip id="437" depart="218.50" from="646320989#0" to="330720250"/>
    <trip id="438" depart="219.00" from="-83808970#0" to="80347021#1"/>
    <trip id="439" depart="219.50" from="-37730532#1" to="154411051#5"/>
    <trip id="440" depart="220.00" from="-93918572#2" to="105600449"/>
    <trip id="441" depart="220.50" from="-106615438#1" to="551899698#1"/>
    <trip id="442" depart="221.00" from="755486093#5" to="37739017#2"/>
    <trip id="443" depart="221.50" from="-39817425#2" to="149116223#3"/>
    <trip id="444" depart="222.00" from="112568330" to="28106642#1"/>
    <trip id="445" depart="222.50" from="344744212#2" to="134756559#1"/>
    <trip id="446" depart="223.00" from="-89418937#1" to="59618369#3"/>
    <trip id="447" depart="223.50" from="-58780683#0" to="132017291#15"/>
    <trip id="448" depart="224.00" from="154500706#0" to="-925606978#0"/>
    <trip id="449" depart="224.50" from="243127219#1" to="257800509"/>
    <trip id="450" depart="225.00" from="952305493#1" to="111238584#2"/>
    <trip id="451" depart="225.50" from="882052277" to="37387153#7"/>
    <trip id="452" depart="226.00" from="1055973952#5" to="25569114#5"/>
    <trip id="453" depart="226.50" from="37640546#4" to="42028905#1"/>
    <trip id="454" depart="227.00" from="-132316386" to="306423780#1"/>
    <trip id="455" depart="227.50" from="160591231#4" to="765105683#7"/>
    <trip id="456" depart="228.00" from="106836310#3" to="50625835#1"/>
    <trip id="457" depart="228.50" from="28193044" to="1182743752"/>
    <trip id="458" depart="229.00" from="332722107#3" to="332306558#2"/>
    <trip id="459" depart="229.50" from="37464534#1" to="397809399#1"/>
    <trip id="460" depart="230.00" from="36944291" to="58768055#11"/>
    <trip id="461" depart="230.50" from="319756521#5" to="764003828#4"/>
    <trip id="462" depart="231.00" from="36725592#1" to="1117205705#2"/>
    <trip id="463" depart="231.50" from="134640686#1" to="26982395#6"/>
    <trip id="464" depart="232.00" from="395600340#3" to="-170469863#2"/>
    <trip id="465" depart="232.50" from="108637165#6" to="426578845#5"/>
    <trip id="466" depart="233.00" from="-452931327#10" to="-326284077"/>
    <trip id="467" depart="233.50" from="22896955" to="880575679#0"/>
    <trip id="468" depart="234.00" from="207858427#0" to="80376790#6"/>
    <trip id="469" depart="234.50" from="572714687#5" to="106260368#5"/>
    <trip id="470" depart="235.00" from="561515113#6" to="165339488#2"/>
    <trip id="471" depart="235.50" from="49581767#5" to="424269159#0"/>
    <trip id="472" depart="236.00" from="111995419#2" to="-240482838#1"/>
    <trip id="473" depart="236.50" from="873283816" to="-369511961#11"/>
    <trip id="474" depart="237.00" from="875445778#1" to="6502123#8"/>
    <trip id="475" depart="237.50" from="38280237#0" to="890119486#2"/>
    <trip id="476" depart="238.00" from="876114770" to="551899698#1"/>
    <trip id="477" depart="238.50" from="1167094067#7" to="49047582#0"/>
    <trip id="478" depart="239.00" from="-108329426#3" to="23034856#1"/>
    <trip id="479" depart="239.50" from="144874008#2" to="37679200#8"/>
    <trip id="480" depart="240.00" from="37290628#2" to="27782022#8"/>
    <trip id="481" depart="240.50" from="559747872#0" to="8272313#6"/>
    <trip id="482" depart="241.00" from="-23683989#9" to="-893901261"/>
    <trip id="483" depart="241.50" from="-111981881#1" to="697584771#0"/>
    <trip id="484" depart="242.00" from="23182366#3" to="80869692#0"/>
    <trip id="485" depart="242.50" from="-75776791#1" to="-134460776#8"/>
    <trip id="486" depart="243.00" from="561062056#0" to="793496327#0"/>
    <trip id="487" depart="243.50" from="1096795080#0" to="134109954#4"/>
    <trip id="488" depart="244.00" from="-37468446#1" to="835696376#3"/>
    <trip id="489" depart="244.50" from="1102250287#2" to="173047160"/>
    <trip id="490" depart="245.00" from="-207854783#0" to="727581415#1"/>
    <trip id="491" depart="245.50" from="-36934168" to="149819238#0"/>
    <trip id="492" depart="246.00" from="37278469#6" to="41871143#3"/>
    <trip id="493" depart="246.50" from="83640998#15" to="134572325#0"/>
    <trip id="494" depart="247.00" from="39977271#0" to="-38027669#0"/>
    <trip id="495" depart="247.50" from="133203515#3" to="-193440715#0"/>
    <trip id="496" depart="248.00" from="154844500#0" to="134109953#0"/>
    <trip id="497" depart="248.50" from="839327616#10" to="-111859620#4"/>
    <trip id="498" depart="249.00" from="1170524249" to="149116230#2"/>
    <trip id="499" depart="249.50" from="838833335#1" to="634244204#2"/>
    <trip id="500" depart="250.00" from="-220847823#0" to="37837433#8"/>
    <trip id="501" depart="250.50" from="22954013#4" to="882052275"/>
    <trip id="502" depart="251.00" from="1148433532" to="133266924"/>
    <trip id="503" depart="251.50" from="-56248964#2" to="-257685398#0"/>
    <trip id="504" depart="252.00" from="58692471" to="149822413#1"/>
    <trip id="505" depart="252.50" from="371198936#0" to="36916542#5"/>
    <trip id="506" depart="253.00" from="27781167#0" to="-107460054#3"/>
    <trip id="507" depart="253.50" from="458826259#1" to="1014883461#1"/>
    <trip id="508" depart="254.00" from="-324738170#5" to="25568832#2"/>
    <trip id="509" depart="254.50" from="-149146783#5" to="447495669#1"/>
    <trip id="510" depart="255.00" from="-657572431#3" to="-80046389#0"/>
    <trip id="511" depart="255.50" from="646274915#1" to="112950823#0"/>
    <trip id="512" depart="256.00" from="-379511956#10" to="757788073#1"/>
    <trip id="513" depart="256.50" from="-103504286#1" to="646315024#4"/>
    <trip id="514" depart="257.00" from="-37830783" to="-316299341#0"/>
    <trip id="515" depart="257.50" from="-89420371#2" to="-43685240#0"/>
    <trip id="516" depart="258.00" from="370092974#1" to="-110678664#15"/>
    <trip id="517" depart="258.50" from="-108637180#9" to="49001120#2"/>
    <trip id="518" depart="259.00" from="-8272420#4" to="112610107"/>
    <trip id="519" depart="259.50" from="-443389241#1" to="-130443665#9"/>
    <trip id="520" depart="260.00" from="39977264#1" to="22907794#5"/>
    <trip id="521" depart="260.50" from="40271561#0" to="160584979"/>
    <trip id="522" depart="261.00" from="43976946#5" to="197571733"/>
    <trip id="523" depart="261.50" from="-239720651#3" to="190048068#2"/>
    <trip id="524" depart="262.00" from="835696375" to="-1171577503#1"/>
    <trip id="525" depart="262.50" from="450274975" to="661248640"/>
    <trip id="526" depart="263.00" from="191142224" to="151167656#6"/>
    <trip id="527" depart="263.50" from="874006667#0" to="-134124998#4"/>
    <trip id="528" depart="264.00" from="151212514#4" to="133850204#1"/>
    <trip id="529" depart="264.50" from="37640550#0" to="171040749#1"/>
    <trip id="530" depart="265.00" from="764420807#4" to="-149023979#2"/>
    <trip id="531" depart="265.50" from="-160667647#2" to="315500328#0"/>
    <trip id="532" depart="266.00" from="-148961515#1" to="108646524#6"/>
    <trip id="533" depart="266.50" from="326284077" to="23315055#1"/>
    <trip id="534" depart="267.00" from="111596216#7" to="95685951"/>
    <trip id="535" depart="267.50" from="207858426" to="149819239#1"/>
    <trip id="536" depart="268.00" from="28107383#1" to="-196325888#0"/>
    <trip id="537" depart="268.50" from="37837438" to="621959187#1"/>
    <trip id="538" depart="269.00" from="36865706#1" to="454001361#1"/>
    <trip id="539" depart="269.50" from="38103321" to="-791156944"/>
    <trip id="540" depart="270.00" from="135863195#0" to="-862454068#2"/>
    <trip id="541" depart="270.50" from="111995421#0" to="149819232#4"/>
    <trip id="543" depart="271.50" from="134009730#0" to="375019457#0"/>
    <trip id="544" depart="272.00" from="1181812801#1" to="-37973572#3"/>
    <trip id="545" depart="272.50" from="80877389#6" to="-135555668#2"/>
    <trip id="546" depart="273.00" from="572714697#1" to="-182851488"/>
    <trip id="547" depart="273.50" from="-197571749" to="40920409#0"/>
    <trip id="548" depart="274.00" from="50625831#0" to="243354139#0"/>
    <trip id="549" depart="274.50" from="257357075#12" to="251662015"/>
    <trip id="550" depart="275.00" from="1117123169#3" to="-257685398#2"/>
    <trip id="551" depart="275.50" from="1130924054#0" to="375045488#2"/>
    <trip id="552" depart="276.00" from="40745985" to="666410867#1"/>
    <trip id="553" depart="276.50" from="38103321" to="876131441"/>
    <trip id="554" depart="277.00" from="28106606#1" to="1177312274#2"/>
    <trip id="555" depart="277.50" from="251378195#1" to="-757698004#1"/>
    <trip id="556" depart="278.00" from="36927091#0" to="-83710622"/>
    <trip id="557" depart="278.50" from="-23683989#6" to="59618371"/>
    <trip id="558" depart="279.00" from="116810542#5" to="441673975#1"/>
    <trip id="559" depart="279.50" from="243505198#0" to="554266635#2"/>
    <trip id="560" depart="280.00" from="58413954#0" to="881905846#0"/>
    <trip id="561" depart="280.50" from="552361913#7" to="319756521#11"/>
    <trip id="562" depart="281.00" from="360136478#2" to="-110678682#0"/>
    <trip id="563" depart="281.50" from="813257273#0" to="572784463#1"/>
    <trip id="564" depart="282.00" from="103504329#1" to="-482702559"/>
    <trip id="565" depart="282.50" from="378383744#1" to="1117205705#4"/>
    <trip id="566" depart="283.00" from="111995471#3" to="-104390538#1"/>
    <trip id="567" depart="283.50" from="646280627#0" to="256368836"/>
    <trip id="568" depart="284.00" from="130443647#6" to="-37041499#3"/>
    <trip id="569" depart="284.50" from="326284077" to="-111801780#3"/>
    <trip id="570" depart="285.00" from="40356005#1" to="-791466952#1"/>
    <trip id="571" depart="285.50" from="133849456#2" to="1158705769#1"/>
    <trip id="572" depart="286.00" from="1169643151" to="39817426#5"/>
    <trip id="573" depart="286.50" from="43976574" to="257025801#1"/>
    <trip id="574" depart="287.00" from="-173047157#1" to="-130443669#5"/>
    <trip id="575" depart="287.50" from="-397537026" to="327375909"/>
    <trip id="576" depart="288.00" from="37348280#0" to="108637168#0"/>
    <trip id="577" depart="288.50" from="37044363#3" to="170397672#1"/>
    <trip id="578" depart="289.00" from="134640700#3" to="108637175#5"/>
    <trip id="579" depart="289.50" from="40920409#0" to="-23683989#2"/>
    <trip id="580" depart="290.00" from="134124998#0" to="110531716#1"/>
    <trip id="581" depart="290.50" from="37464542#1" to="170397678#3"/>
    <trip id="582" depart="291.00" from="372173610#0" to="-120676228#1"/>
    <trip id="583" depart="291.50" from="129209771" to="292040017"/>
    <trip id="584" depart="292.00" from="-106367443#0" to="111549929#3"/>
    <trip id="585" depart="292.50" from="-681328860" to="-36357294"/>
    <trip id="586" depart="293.00" from="-96185126#1" to="112698199"/>
    <trip id="587" depart="293.50" from="-106367443#1" to="425251864"/>
    <trip id="588" depart="294.00" from="-452931327#10" to="130443643#13"/>
    <trip id="589" depart="294.50" from="37871790#15" to="185594221"/>
    <trip id="590" depart="295.00" from="572744499#2" to="552704373#3"/>
    <trip id="591" depart="295.50" from="-149822410" to="656723485#1"/>
    <trip id="592" depart="296.00" from="-127949021" to="-107289448"/>
    <trip id="593" depart="296.50" from="80716872#1" to="657150061#1"/>
    <trip id="594" depart="297.00" from="24615563" to="257538843#1"/>
    <trip id="595" depart="297.50" from="37973571#10" to="134460789#5"/>
    <trip id="596" depart="298.00" from="-257357075#3" to="-107426187#2"/>
    <trip id="597" depart="298.50" from="111593634#2" to="533837088#2"/>
    <trip id="598" depart="299.00" from="302566463#0" to="58233300#0"/>
    <trip id="599" depart="299.50" from="80376790#6" to="-164045248"/>
    <trip id="600" depart="300.00" from="580542103#0" to="1014883457#1"/>
    <trip id="601" depart="300.50" from="257685415#1" to="22897872#4"/>
    <trip id="602" depart="301.00" from="129252320#0" to="111801786#0"/>
    <trip id="603" depart="301.50" from="111995455#3" to="1135183458#1"/>
    <trip id="604" depart="302.00" from="-41920811#0" to="193440715#0"/>
    <trip id="605" depart="302.50" from="-257171426#0" to="193440709#1"/>
    <trip id="606" depart="303.00" from="757685963#8" to="1171577501"/>
    <trip id="607" depart="303.50" from="38319544#7" to="572714697#1"/>
    <trip id="608" depart="304.00" from="535354040#1" to="-901159183#0"/>
    <trip id="609" depart="304.50" from="-37871790#7" to="-594306218#0"/>
    <trip id="610" depart="305.00" from="28106767#0" to="43907782#0"/>
    <trip id="611" depart="305.50" from="36916541#22" to="-447699318#3"/>
    <trip id="612" depart="306.00" from="43709000#4" to="174466488#0"/>
    <trip id="613" depart="306.50" from="40920406" to="43907780#0"/>
    <trip id="614" depart="307.00" from="135860919#4" to="814585369"/>
    <trip id="615" depart="307.50" from="23262356#3" to="36855977"/>
    <trip id="616" depart="308.00" from="316299338#4" to="657572429#9"/>
    <trip id="617" depart="308.50" from="31860136#7" to="-37908654#0"/>
    <trip id="618" depart="309.00" from="-149146783#15" to="149116225#3"/>
    <trip id="619" depart="309.50" from="1098396206#0" to="108646520#2"/>
    <trip id="620" depart="310.00" from="-134155188#11" to="191532951"/>
    <trip id="621" depart="310.50" from="110904573#4" to="149422199#1"/>
    <trip id="622" depart="311.00" from="-134417955#4" to="580542103#1"/>
    <trip id="623" depart="311.50" from="-154716224" to="657572429#9"/>
    <trip id="624" depart="312.00" from="591803643" to="323978915#2"/>
    <trip id="625" depart="312.50" from="170567934#2" to="154500699#1"/>
    <trip id="626" depart="313.00" from="23054020#6" to="490747922#4"/>
    <trip id="627" depart="313.50" from="741000721#0" to="149190790#1"/>
    <trip id="628" depart="314.00" from="50338646#0" to="37228342#0"/>
    <trip id="629" depart="314.50" from="111504831#0" to="159296195#0"/>
    <trip id="630" depart="315.00" from="-38027982#4" to="-134155196#3"/>
    <trip id="631" depart="315.50" from="-23026016#3" to="757537434#0"/>
    <trip id="632" depart="316.00" from="112568282#20" to="383741243#10"/>
    <trip id="634" depart="317.00" from="-881417249" to="148961531#1"/>
    <trip id="635" depart="317.50" from="134572327#0" to="22897740#10"/>
    <trip id="636" depart="318.00" from="-399631779#3" to="128039749#8"/>
    <trip id="637" depart="318.50" from="106581160#0" to="134124980#0"/>
    <trip id="638" depart="319.00" from="111981879#2" to="29180242"/>
    <trip id="639" depart="319.50" from="476368077" to="371194048#1"/>
    <trip id="640" depart="320.00" from="-148961522#0" to="-185581507#0"/>
    <trip id="641" depart="320.50" from="37464540#4" to="110678664#1"/>
    <trip id="642" depart="321.00" from="38235045#1" to="37329394"/>
    <trip id="643" depart="321.50" from="757788069#1" to="675542937#5"/>
    <trip id="644" depart="322.00" from="111801801#1" to="27781803#8"/>
    <trip id="645" depart="322.50" from="-37640549#1" to="1173244751#1"/>
    <trip id="646" depart="323.00" from="876120664#1" to="38027665#8"/>
    <trip id="647" depart="323.50" from="128039739#3" to="287540612"/>
    <trip id="648" depart="324.00" from="82225016#1" to="111760313#2"/>
    <trip id="649" depart="324.50" from="120649992#1" to="490747922#0"/>
    <trip id="650" depart="325.00" from="524463976#8" to="37640550#11"/>
    <trip id="651" depart="325.50" from="565129129#2" to="40920407#9"/>
    <trip id="652" depart="326.00" from="37640545#7" to="22908417#2"/>
    <trip id="653" depart="326.50" from="364952114#0" to="134690561"/>
    <trip id="654" depart="327.00" from="1149702456#2" to="122700215#1"/>
    <trip id="655" depart="327.50" from="-48275803#4" to="-768645864#4"/>
    <trip id="656" depart="328.00" from="83709549#21" to="170397676#0"/>
    <trip id="657" depart="328.50" from="-80869688#3" to="-36818172#1"/>
    <trip id="658" depart="329.00" from="-154716225#1" to="594306216"/>
    <trip id="659" depart="329.50" from="-22898291#0" to="459789838#5"/>
    <trip id="660" depart="330.00" from="572744581#0" to="696886240#5"/>
    <trip id="661" depart="330.50" from="-120517721" to="1148510882#1"/>
    <trip id="662" depart="331.00" from="43012899#7" to="-323026984"/>
    <trip id="663" depart="331.50" from="120649992#2" to="-39817425#2"/>
    <trip id="665" depart="332.50" from="499694887" to="-39977268#3"/>
    <trip id="666" depart="333.00" from="134460789#3" to="134148121#1"/>
    <trip id="667" depart="333.50" from="37449247#0" to="-932418340#0"/>
    <trip id="668" depart="334.00" from="134756557#3" to="110678679#1"/>
    <trip id="669" depart="334.50" from="40735734#1" to="149190775#2"/>
    <trip id="670" depart="335.00" from="217850378" to="111760289"/>
    <trip id="671" depart="335.50" from="499694884#6" to="154844473"/>
    <trip id="672" depart="336.00" from="572744581#0" to="127736999#5"/>
    <trip id="673" depart="336.50" from="83709549#1" to="898593569#1"/>
    <trip id="674" depart="337.00" from="149116218#1" to="1102650221#0"/>
    <trip id="675" depart="337.50" from="122301988#1" to="22954013#6"/>
    <trip id="676" depart="338.00" from="875445776#1" to="572328744#4"/>
    <trip id="677" depart="338.50" from="48801898#1" to="-36857683#3"/>
    <trip id="678" depart="339.00" from="-893901267#0" to="36916541#34"/>
    <trip id="679" depart="339.50" from="657572415#0" to="239720651#8"/>
    <trip id="680" depart="340.00" from="-230193701#1" to="59619000"/>
    <trip id="681" depart="340.50" from="58779713#1" to="110678679#5"/>
    <trip id="682" depart="341.00" from="42737802#2" to="108637174#0"/>
    <trip id="683" depart="341.50" from="757534983#4" to="-37679201#0"/>
    <trip id="684" depart="342.00" from="134460789#18" to="83640858#0"/>
    <trip id="685" depart="342.50" from="-763118489" to="149419435#1"/>
    <trip id="686" depart="343.00" from="112610156#4" to="-110678682#9"/>
    <trip id="687" depart="343.50" from="-133270848#1" to="186413440"/>
    <trip id="688" depart="344.00" from="-825714831" to="95685949#0"/>
    <trip id="689" depart="344.50" from="118304192#0" to="-111549936"/>
    <trip id="690" depart="345.00" from="81400143#1" to="58768063#0"/>
    <trip id="691" depart="345.50" from="36852535#0" to="490747921#1"/>
    <trip id="692" depart="346.00" from="-37140690" to="110801311#3"/>
    <trip id="693" depart="346.50" from="572375444" to="37981427#0"/>
    <trip id="694" depart="347.00" from="-37305404#10" to="38103357#5"/>
    <trip id="695" depart="347.50" from="135860918#1" to="-104148308#1"/>
    <trip id="696" depart="348.00" from="-160587538#0" to="1058894640#1"/>
    <trip id="697" depart="348.50" from="572744575#2" to="234282661#1"/>
    <trip id="698" depart="349.00" from="38319544#24" to="22954049"/>
    <trip id="699" depart="349.50" from="-249523073#1" to="110904582#8"/>
    <trip id="700" depart="350.00" from="1095219590#0" to="-127737007#3"/>
    <trip id="701" depart="350.50" from="133849456#2" to="49723042#2"/>
    <trip id="703" depart="351.50" from="757528301#0" to="287836711#0"/>
    <trip id="704" depart="352.00" from="-1102649877#2" to="207860567"/>
    <trip id="705" depart="352.50" from="-839327616#7" to="-372496747#0"/>
    <trip id="706" depart="353.00" from="134124991#1" to="323978915#15"/>
    <trip id="707" depart="353.50" from="-83710623" to="134460774#8"/>
    <trip id="708" depart="354.00" from="37140611#1" to="-160587538#6"/>
    <trip id="709" depart="354.50" from="881905846#10" to="-135860931#0"/>
    <trip id="711" depart="355.50" from="925606978#4" to="239720651#14"/>
    <trip id="712" depart="356.00" from="127949008#0" to="154889914#0"/>
    <trip id="713" depart="356.50" from="332306556#2" to="893901258#1"/>
    <trip id="714" depart="357.00" from="-932750555" to="-106616330#0"/>
    <trip id="715" depart="357.50" from="469372933" to="116810527"/>
    <trip id="716" depart="358.00" from="39671240#0" to="359596381"/>
    <trip id="717" depart="358.50" from="43684741#6" to="40745997#4"/>
    <trip id="718" depart="359.00" from="111801790#1" to="-1177239723#1"/>
    <trip id="719" depart="359.50" from="22956026#0" to="562077270#3"/>
    <trip id="720" depart="360.00" from="-447701119#1" to="48122676#1"/>
    <trip id="721" depart="360.50" from="149116234#1" to="37973572#4"/>
    <trip id="722" depart="361.00" from="324352207#8" to="561528801"/>
    <trip id="723" depart="361.50" from="-135860932#11" to="48063707#1"/>
    <trip id="724" depart="362.00" from="148961532" to="111238563#0"/>
    <trip id="725" depart="362.50" from="-129252342#5" to="-60131972#1"/>
    <trip id="726" depart="363.00" from="-127737007#4" to="819816251"/>
    <trip id="727" depart="363.50" from="185581486#1" to="925814524"/>
    <trip id="728" depart="364.00" from="22907780#4" to="1055432256"/>
    <trip id="729" depart="364.50" from="40760636#1" to="-58233300#0"/>
    <trip id="730" depart="365.00" from="113734603#2" to="481545211#8"/>
    <trip id="731" depart="365.50" from="626663895" to="1132712308#1"/>
    <trip id="732" depart="366.00" from="-315021655#1" to="127737001#0"/>
    <trip id="733" depart="366.50" from="696914468#0" to="41900657#0"/>
    <trip id="734" depart="367.00" from="738276511#4" to="132316386"/>
    <trip id="735" depart="367.50" from="881245056" to="182677999"/>
    <trip id="736" depart="368.00" from="160600493#0" to="814585369"/>
    <trip id="737" depart="368.50" from="189868533#3" to="533540038#0"/>
    <trip id="738" depart="369.00" from="38319544#2" to="-149822412#0"/>
    <trip id="739" depart="369.50" from="28106933#1" to="572744581#1"/>
    <trip id="740" depart="370.00" from="22954833#16" to="112568295"/>
    <trip id="741" depart="370.50" from="-160591234#3" to="37464534#0"/>
    <trip id="742" depart="371.00" from="110531716#0" to="302238837#0"/>
    <trip id="743" depart="371.50" from="133960538#2" to="37908654#0"/>
    <trip id="744" depart="372.00" from="112950831#0" to="-1170352353#0"/>
    <trip id="745" depart="372.50" from="646294502#1" to="118304185#11"/>
    <trip id="746" depart="373.00" from="992676609#0" to="108646518#1"/>
    <trip id="747" depart="373.50" from="890119490#2" to="83709549#11"/>
    <trip id="748" depart="374.00" from="-154716196#9" to="36876578#1"/>
    <trip id="749" depart="374.50" from="1158706538#0" to="532288764#5"/>
    <trip id="751" depart="375.50" from="-37715948#4" to="312246836#1"/>
    <trip id="752" depart="376.00" from="44641744#1" to="-112002461#2"/>
    <trip id="753" depart="376.50" from="-149023979#2" to="481220287#2"/>
    <trip id="754" depart="377.00" from="1167094068#7" to="130443663#2"/>
    <trip id="755" depart="377.50" from="23463859#1" to="303651706#0"/>
    <trip id="756" depart="378.00" from="37468444#1" to="83709549#35"/>
    <trip id="757" depart="378.50" from="1174493054#3" to="443389241#0"/>
    <trip id="758" depart="379.00" from="243504570#0" to="22956122#4"/>
    <trip id="759" depart="379.50" from="129780023#1" to="37140690"/>
    <trip id="760" depart="380.00" from="-893901258#1" to="-23589864#1"/>
    <trip id="761" depart="380.50" from="397430745#1" to="185581498"/>
    <trip id="762" depart="381.00" from="127736993#2" to="252268251"/>
    <trip id="763" depart="381.50" from="102035618#1" to="106615437#3"/>
    <trip id="764" depart="382.00" from="135733958#1" to="966240516"/>
    <trip id="765" depart="382.50" from="106833598" to="80877389#7"/>
    <trip id="766" depart="383.00" from="154986394#4" to="-257800506#1"/>
    <trip id="767" depart="383.50" from="58779941" to="149422210#1"/>
    <trip id="768" depart="384.00" from="748671324#0" to="149146772#0"/>
    <trip id="769" depart="384.50" from="-182986061" to="37772595#8"/>
    <trip id="770" depart="385.00" from="58413955#3" to="1121159830"/>
    <trip id="771" depart="385.50" from="112610112#3" to="-134690526#6"/>
    <trip id="772" depart="386.00" from="22907738#11" to="745220416#2"/>
    <trip id="773" depart="386.50" from="58779715#0" to="38320044#5"/>
    <trip id="774" depart="387.00" from="81157268#0" to="36876578#8"/>
    <trip id="775" depart="387.50" from="481220287#3" to="192219877#1"/>
    <trip id="776" depart="388.00" from="-287540612" to="-607393606#0"/>
    <trip id="777" depart="388.50" from="-37305404#12" to="49024291#4"/>
    <trip id="778" depart="389.00" from="-112002478#4" to="239720651#0"/>
    <trip id="779" depart="389.50" from="116810574" to="551875154#0"/>
    <trip id="780" depart="390.00" from="23027994#1" to="318054660#1"/>
    <trip id="781" depart="390.50" from="-174466482#0" to="1117205706#3"/>
    <trip id="782" depart="391.00" from="996232969#0" to="397430745#1"/>
    <trip id="783" depart="391.50" from="193440711#2" to="4546578#0"/>
    <trip id="784" depart="392.00" from="56015537#6" to="-149116219#0"/>
    <trip id="785" depart="392.50" from="880575680" to="36927094#3"/>
    <trip id="786" depart="393.00" from="135860931#13" to="37761134#4"/>
    <trip id="787" depart="393.50" from="112568299#1" to="683500048"/>
    <trip id="788" depart="394.00" from="44468712#21" to="36913261#2"/>
    <trip id="789" depart="394.50" from="-487170680" to="875446016#2"/>
    <trip id="790" depart="395.00" from="134249210" to="79634412#2"/>
    <trip id="791" depart="395.50" from="-134124994#6" to="-264869884"/>
    <trip id="792" depart="396.00" from="-38081514#1" to="-39977260#0"/>
    <trip id="793" depart="396.50" from="1115285029" to="38308631"/>
    <trip id="794" depart="397.00" from="112568339#3" to="8272356#7"/>
    <trip id="795" depart="397.50" from="739054396#2" to="59619002"/>
    <trip id="796" depart="398.00" from="-89418947#9" to="36843404#0"/>
    <trip id="797" depart="398.50" from="23026369#0" to="-28107012"/>
    <trip id="798" depart="399.00" from="1098396206#0" to="23026070#1"/>
    <trip id="799" depart="399.50" from="166727313#0" to="-40735739#2"/>
    <trip id="800" depart="400.00" from="8272362" to="-38027668#2"/>
    <trip id="801" depart="400.50" from="36936416#14" to="39773187#1"/>
    <trip id="802" depart="401.00" from="28107378#0" to="58780677#3"/>
    <trip id="803" depart="401.50" from="23262200#14" to="572748494#3"/>
    <trip id="804" depart="402.00" from="-112610106#1" to="-120676228#2"/>
    <trip id="805" depart="402.50" from="359380195#0" to="26540081#5"/>
    <trip id="806" depart="403.00" from="36873878#0" to="451543648"/>
    <trip id="807" depart="403.50" from="133261325#4" to="36889333"/>
    <trip id="808" depart="404.00" from="160601729#1" to="359304569#2"/>
    <trip id="809" depart="404.50" from="107425018#0" to="862447331#1"/>
    <trip id="810" depart="405.00" from="154500693#3" to="551899698#3"/>
    <trip id="811" depart="405.50" from="37640545#12" to="111339652#2"/>
    <trip id="812" depart="406.00" from="-149868584#6" to="-134009740#3"/>
    <trip id="813" depart="406.50" from="134572327#1" to="167457302"/>
    <trip id="814" depart="407.00" from="-62094934#1" to="309378439"/>
    <trip id="815" depart="407.50" from="110904638#3" to="39685721#6"/>
    <trip id="816" depart="408.00" from="39685718#0" to="651764272#9"/>
    <trip id="817" depart="408.50" from="881905851#4" to="-323026984"/>
    <trip id="818" depart="409.00" from="1170524249" to="25210754#0"/>
    <trip id="819" depart="409.50" from="111262067#7" to="154716224"/>
    <trip id="820" depart="410.00" from="103504330" to="1033438196#1"/>
    <trip id="821" depart="410.50" from="-200750063" to="110904648#2"/>
    <trip id="822" depart="411.00" from="124804821#1" to="323978916#0"/>
    <trip id="823" depart="411.50" from="-881679701#1" to="659342832#14"/>
    <trip id="824" depart="412.00" from="-39977258" to="1126552148#4"/>
    <trip id="825" depart="412.50" from="251378194#0" to="111815983#11"/>
    <trip id="826" depart="413.00" from="42737802#2" to="185581486#1"/>
    <trip id="827" depart="413.50" from="185298595" to="185581492#0"/>
    <trip id="828" depart="414.00" from="110678682#7" to="-108722025#4"/>
    <trip id="829" depart="414.50" from="834049653#3" to="191142788"/>
    <trip id="830" depart="415.00" from="875446015#0" to="-791466952#1"/>
    <trip id="831" depart="415.50" from="112950876" to="-130443630#14"/>
    <trip id="832" depart="416.00" from="160584976" to="688443266#1"/>
    <trip id="833" depart="416.50" from="36903944#5" to="154889920#2"/>
    <trip id="834" depart="417.00" from="220847832" to="59712410#0"/>
    <trip id="835" depart="417.50" from="134148121#1" to="688443266#1"/>
    <trip id="836" depart="418.00" from="38320024#0" to="44468712#22"/>
    <trip id="837" depart="418.50" from="1167094068#11" to="133849447"/>
    <trip id="838" depart="419.00" from="23683989#9" to="-58779937#2"/>
    <trip id="839" depart="419.50" from="23034777#0" to="-149023979#3"/>
    <trip id="840" depart="420.00" from="170397667#0" to="44468712#35"/>
    <trip id="841" depart="420.50" from="106332337" to="925609106#1"/>
    <trip id="842" depart="421.00" from="37480173#14" to="-257025801#0"/>
    <trip id="843" depart="421.50" from="881905847" to="133165504#2"/>
    <trip id="844" depart="422.00" from="481463189#1" to="1149690287#2"/>
    <trip id="845" depart="422.50" from="824542215#1" to="43633786#5"/>
    <trip id="846" depart="423.00" from="-58780682#4" to="192302042"/>
    <trip id="847" depart="423.50" from="164045248" to="-120649992#2"/>
    <trip id="848" depart="424.00" from="-369844983#4" to="1135183458#0"/>
    <trip id="849" depart="424.50" from="149819227#0" to="149864370#1"/>
    <trip id="850" depart="425.00" from="28193008#2" to="208420936"/>
    <trip id="851" depart="425.50" from="1116516518#1" to="318996538#4"/>
    <trip id="852" depart="426.00" from="-405900731#0" to="932750553#1"/>
    <trip id="853" depart="426.50" from="39971279#7" to="111504831#3"/>
    <trip id="854" depart="427.00" from="111859620#1" to="572748521#0"/>
    <trip id="855" depart="427.50" from="209264725" to="38306581#6"/>
    <trip id="856" depart="428.00" from="1094437564#0" to="563843025#0"/>
    <trip id="857" depart="428.50" from="116810563" to="37688113#2"/>
    <trip id="858" depart="429.00" from="890119486#0" to="27781952#2"/>
    <trip id="859" depart="429.50" from="483629577#3" to="39977265"/>
    <trip id="860" depart="430.00" from="37679199#5" to="-110678682#8"/>
    <trip id="861" depart="430.50" from="149819232#5" to="876120664#3"/>
    <trip id="862" depart="431.00" from="449972311#0" to="48063707#1"/>
    <trip id="863" depart="431.50" from="251378193#2" to="39817426#0"/>
    <trip id="864" depart="432.00" from="257028824#2" to="-41670979#1"/>
    <trip id="865" depart="432.50" from="323026984" to="330720250"/>
    <trip id="866" depart="433.00" from="572748521#1" to="-37679707"/>
    <trip id="867" depart="433.50" from="37480173#6" to="-111801830#3"/>
    <trip id="868" depart="434.00" from="83709549#35" to="-230235356#3"/>
    <trip id="869" depart="434.50" from="-111238565#0" to="111859620#1"/>
    <trip id="870" depart="435.00" from="-38027983#3" to="37908662#0"/>
    <trip id="871" depart="435.50" from="132527899#5" to="48056807#1"/>
    <trip id="872" depart="436.00" from="80451878#1" to="675374232"/>
    <trip id="873" depart="436.50" from="397430749#0" to="-134417955#9"/>
    <trip id="874" depart="437.00" from="-37228341#0" to="-685440561#0"/>
    <trip id="875" depart="437.50" from="111596216#4" to="37468443#2"/>
    <trip id="876" depart="438.00" from="193440710#0" to="111859620#4"/>
    <trip id="877" depart="438.50" from="-43837961#3" to="80339835"/>
    <trip id="878" depart="439.00" from="112002480#1" to="1189684994"/>
    <trip id="879" depart="439.50" from="43684742#5" to="397809399#1"/>
    <trip id="880" depart="440.00" from="36258335#0" to="37973567#3"/>
    <trip id="881" depart="440.50" from="287672152#1" to="-58413964#7"/>
    <trip id="882" depart="441.00" from="-875435450#0" to="24573930#5"/>
    <trip id="883" depart="441.50" from="-79606559#2" to="881245055#1"/>
    <trip id="884" depart="442.00" from="108637181#1" to="110904623#0"/>
    <trip id="885" depart="442.50" from="-659342821" to="38103313#5"/>
    <trip id="886" depart="443.00" from="111238580#0" to="1171577492"/>
    <trip id="887" depart="443.50" from="816387299#1" to="499694884#5"/>
    <trip id="888" depart="444.00" from="1055733688#1" to="-257538844#2"/>
    <trip id="889" depart="444.50" from="37449247#8" to="130443636#9"/>
    <trip id="890" depart="445.00" from="890119492#0" to="572714696#1"/>
    <trip id="891" depart="445.50" from="855899675#7" to="551899698#1"/>
    <trip id="892" depart="446.00" from="107426152#0" to="110904573#2"/>
    <trip id="893" depart="446.50" from="38027665#2" to="116810565"/>
    <trip id="894" depart="447.00" from="134650932#1" to="106255758#1"/>
    <trip id="895" depart="447.50" from="151212520#2" to="-62094934#1"/>
    <trip id="896" depart="448.00" from="22876733#2" to="819816249"/>
    <trip id="897" depart="448.50" from="37761137#0" to="-36357294"/>
    <trip id="898" depart="449.00" from="295464103" to="28106636#3"/>
    <trip id="899" depart="449.50" from="-85426929#2" to="37640549#1"/>
    <trip id="900" depart="450.00" from="207858427#0" to="368807875#11"/>
    <trip id="901" depart="450.50" from="-133259884#0" to="134417913#1"/>
    <trip id="902" depart="451.00" from="38081494#4" to="-207854783#1"/>
    <trip id="903" depart="451.50" from="43633786#5" to="-104148308#0"/>
    <trip id="904" depart="452.00" from="23026016#3" to="816737047"/>
    <trip id="905" depart="452.50" from="132316388#2" to="82215683#8"/>
    <trip id="906" depart="453.00" from="660243735#2" to="160587545#0"/>
    <trip id="907" depart="453.50" from="-591803643" to="874650462#1"/>
    <trip id="908" depart="454.00" from="111504825#5" to="370092974#1"/>
    <trip id="909" depart="454.50" from="758665676" to="-166727313#1"/>
    <trip id="910" depart="455.00" from="243505198#2" to="23027995#11"/>
    <trip id="911" depart="455.50" from="38228091#4" to="824542215#11"/>
    <trip id="912" depart="456.00" from="771302026" to="-43709002#6"/>
    <trip id="913" depart="456.50" from="667827206" to="-43837961#3"/>
    <trip id="914" depart="457.00" from="80376790#16" to="966689854#2"/>
    <trip id="915" depart="457.50" from="129305557#0" to="179917799#5"/>
    <trip id="916" depart="458.00" from="82207176#1" to="873283815#0"/>
    <trip id="917" depart="458.50" from="81096855#0" to="681328860"/>
    <trip id="918" depart="459.00" from="-106615437#3" to="257028824#0"/>
    <trip id="919" depart="459.50" from="-23566893#1" to="89420370#2"/>
    <trip id="920" depart="460.00" from="106620901#0" to="925814524"/>
    <trip id="921" depart="460.50" from="22907794#9" to="174466482#0"/>
    <trip id="922" depart="461.00" from="82290358" to="60750194#2"/>
    <trip id="923" depart="461.50" from="149146787#7" to="-58414208#2"/>
    <trip id="924" depart="462.00" from="-254428900#1" to="-39831540#11"/>
    <trip id="925" depart="462.50" from="148961537#0" to="106268582#2"/>
    <trip id="926" depart="463.00" from="-552143226#3" to="40760632"/>
    <trip id="927" depart="463.50" from="48056807#1" to="257027154"/>
    <trip id="928" depart="464.00" from="417256152" to="-43836955#5"/>
    <trip id="929" depart="464.50" from="595247604#2" to="756932040#3"/>
    <trip id="930" depart="465.00" from="56244275#5" to="207858428#1"/>
    <trip id="931" depart="465.50" from="-179424270" to="37640546#2"/>
    <trip id="932" depart="466.00" from="-531477507#2" to="-369511399#5"/>
    <trip id="933" depart="466.50" from="111549929#10" to="1033438197"/>
    <trip id="934" depart="467.00" from="102035599#1" to="-89420371#2"/>
    <trip id="935" depart="467.50" from="40870793" to="85427043"/>
    <trip id="936" depart="468.00" from="1096502746#4" to="399631780#2"/>
    <trip id="937" depart="468.50" from="-107309874#0" to="37278469#6"/>
    <trip id="938" depart="469.00" from="37730532#8" to="-134417955#3"/>
    <trip id="939" depart="469.50" from="-264869636#1" to="111702115#0"/>
    <trip id="940" depart="470.00" from="132316370#1" to="186760727#2"/>
    <trip id="941" depart="470.50" from="740946653#2" to="38081511#1"/>
    <trip id="942" depart="471.00" from="110904586#3" to="-251612439"/>
    <trip id="943" depart="471.50" from="79606555#7" to="111238582#0"/>
    <trip id="944" depart="472.00" from="294507534#6" to="-81632513#0"/>
    <trip id="945" depart="472.50" from="-36857299#2" to="-38027102#9"/>
    <trip id="946" depart="473.00" from="405900734#5" to="30495198#6"/>
    <trip id="947" depart="473.50" from="133259886#1" to="23463669#1"/>
    <trip id="948" depart="474.00" from="149415691#3" to="23054020#6"/>
    <trip id="949" depart="474.50" from="37138417#8" to="-81124948#0"/>
    <trip id="950" depart="475.00" from="-881245057#0" to="435787898#7"/>
    <trip id="951" depart="475.50" from="656301255#0" to="-154716196#8"/>
    <trip id="952" depart="476.00" from="135738996#6" to="38081515"/>
    <trip id="953" depart="476.50" from="-154986395#11" to="254427254#1"/>
    <trip id="954" depart="477.00" from="-135555668#0" to="23262356#0"/>
    <trip id="955" depart="477.50" from="170397682#0" to="257441888"/>
    <trip id="956" depart="478.00" from="-38027668#13" to="112698199"/>
    <trip id="957" depart="478.50" from="190658505#4" to="-243506937#0"/>
    <trip id="958" depart="479.00" from="-635573019" to="27781843#1"/>
    <trip id="960" depart="480.00" from="499694885#0" to="149819232#3"/>
    <trip id="961" depart="480.50" from="179917799#10" to="149864368#2"/>
    <trip id="962" depart="481.00" from="-134460776#0" to="154500688#4"/>
    <trip id="963" depart="481.50" from="49723042#0" to="39971279#8"/>
    <trip id="964" depart="482.00" from="129252320#3" to="569615074#4"/>
    <trip id="966" depart="483.00" from="-130443630#9" to="116810518#0"/>
    <trip id="967" depart="483.50" from="-135860936#6" to="95615289#1"/>
    <trip id="968" depart="484.00" from="81792743#0" to="-135860936#6"/>
    <trip id="969" depart="484.50" from="81672207#0" to="-111801830#8"/>
    <trip id="970" depart="485.00" from="132419488" to="454001361#2"/>
    <trip id="971" depart="485.50" from="43012021#1" to="884073633#0"/>
    <trip id="972" depart="486.00" from="363701247#0" to="134640686#0"/>
    <trip id="973" depart="486.50" from="95514276#2" to="130443659#8"/>
    <trip id="974" depart="487.00" from="646274912" to="770822811"/>
    <trip id="975" depart="487.50" from="1183920586#9" to="37772602#1"/>
    <trip id="976" depart="488.00" from="37044363#0" to="23066446#3"/>
    <trip id="977" depart="488.50" from="368807876#17" to="1169000267"/>
    <trip id="978" depart="489.00" from="-481220287#2" to="23054020#0"/>
    <trip id="979" depart="489.50" from="207858124#2" to="40029734"/>
    <trip id="980" depart="490.00" from="-765543785#1" to="-103428632#1"/>
    <trip id="981" depart="490.50" from="-111801792" to="111504819#1"/>
    <trip id="982" depart="491.00" from="37348277#3" to="23182358#9"/>
    <trip id="983" depart="491.50" from="208420936" to="572744599#0"/>
    <trip id="984" depart="492.00" from="-881245057#3" to="116810555"/>
    <trip id="985" depart="492.50" from="105601667#0" to="824542215#27"/>
    <trip id="986" depart="493.00" from="38306581#3" to="-23490352#0"/>
    <trip id="987" depart="493.50" from="502438902#3" to="134572327#3"/>
    <trip id="988" depart="494.00" from="43012899#1" to="697584765#1"/>
    <trip id="989" depart="494.50" from="-1089005086#3" to="-676847690#0"/>
    <trip id="990" depart="495.00" from="-22897872#4" to="-111981870#0"/>
    <trip id="991" depart="495.50" from="27781803#6" to="38081508#3"/>
    <trip id="992" depart="496.00" from="-132316384#2" to="41245532#3"/>
    <trip id="993" depart="496.50" from="130443659#2" to="-893901264"/>
    <trip id="994" depart="497.00" from="-688870854#3" to="657572423"/>
    <trip id="995" depart="497.50" from="-134155188#9" to="190048068#4"/>
    <trip id="996" depart="498.00" from="107309874#0" to="563843025#1"/>
    <trip id="997" depart="498.50" from="39231924#3" to="112002475"/>
    <trip id="998" depart="499.00" from="27781824#0" to="37679200#21"/>
    <trip id="999" depart="499.50" from="111504819#0" to="111549936"/>
    <trip id="1000" depart="500.00" from="-37730532#5" to="37449253#3"/>
    <trip id="1001" depart="500.50" from="-757359035#5" to="1115314971"/>
    <trip id="1002" depart="501.00" from="-134891254#3" to="83709549#28"/>
    <trip id="1004" depart="502.00" from="31761383#4" to="135747092#3"/>
    <trip id="1005" depart="502.50" from="160587537#1" to="881245049#1"/>
    <trip id="1006" depart="503.00" from="8272362" to="37679196#1"/>
    <trip id="1007" depart="503.50" from="4549612#5" to="112002473#0"/>
    <trip id="1008" depart="504.00" from="133259891" to="-37837433#0"/>
    <trip id="1009" depart="504.50" from="1203890045#2" to="435787897#0"/>
    <trip id="1010" depart="505.00" from="149819225#0" to="60132593"/>
    <trip id="1011" depart="505.50" from="1095217615#20" to="38230512"/>
    <trip id="1012" depart="506.00" from="49304432" to="80728666#1"/>
    <trip id="1013" depart="506.50" from="23182423#4" to="876124550#0"/>
    <trip id="1014" depart="507.00" from="23088979#1" to="-332722107#5"/>
    <trip id="1015" depart="507.50" from="-855883542#5" to="-657572429#5"/>
    <trip id="1016" depart="508.00" from="36725593#3" to="813257273#1"/>
    <trip id="1017" depart="508.50" from="58414208#2" to="-174466482#0"/>
    <trip id="1018" depart="509.00" from="38280238#0" to="-572748521#0"/>
    <trip id="1019" depart="509.50" from="104148308#1" to="37688111"/>
    <trip id="1020" depart="510.00" from="28106958#0" to="676841240#3"/>
    <trip id="1021" depart="510.50" from="-561515113#3" to="44044489#1"/>
    <trip id="1022" depart="511.00" from="38280237#0" to="24615583#4"/>
    <trip id="1023" depart="511.50" from="151212521#4" to="667668276#4"/>
    <trip id="1024" depart="512.00" from="111801794" to="862447333#5"/>
    <trip id="1025" depart="512.50" from="-108722025#6" to="824542215#23"/>
    <trip id="1026" depart="513.00" from="873278978#0" to="-251612439"/>
    <trip id="1027" depart="513.50" from="996232968#5" to="160600494#0"/>
    <trip id="1028" depart="514.00" from="-85426929#5" to="302596648#1"/>
    <trip id="1029" depart="514.50" from="-626663506#0" to="80869690#0"/>
    <trip id="1030" depart="515.00" from="23027994#9" to="48056810#4"/>
    <trip id="1031" depart="515.50" from="122258521#0" to="23026108#2"/>
    <trip id="1032" depart="516.00" from="1148510884#5" to="106833598"/>
    <trip id="1033" depart="516.50" from="178996141#6" to="182986063#2"/>
    <trip id="1034" depart="517.00" from="-209264417" to="893901260"/>
    <trip id="1035" depart="517.50" from="149190771#1" to="58770833#0"/>
    <trip id="1036" depart="518.00" from="77914306#0" to="127949013#0"/>
    <trip id="1037" depart="518.50" from="133198385#0" to="253301352"/>
    <trip id="1038" depart="519.00" from="-757698004#1" to="-37480172#1"/>
    <trip id="1039" depart="519.50" from="102035599#1" to="82215682#1"/>
    <trip id="1041" depart="520.50" from="-38081505#0" to="112950858"/>
    <trip id="1042" depart="521.00" from="121952569#7" to="58413962#5"/>
    <trip id="1043" depart="521.50" from="163979749#6" to="37290625#11"/>
    <trip id="1044" depart="522.00" from="37640545#1" to="106332325#0"/>
    <trip id="1045" depart="522.50" from="559744473#3" to="876114768"/>
    <trip id="1046" depart="523.00" from="359380196#1" to="172399127#1"/>
    <trip id="1047" depart="523.50" from="-41978954#1" to="499688748#3"/>
    <trip id="1048" depart="524.00" from="-424518802#0" to="397537027#2"/>
    <trip id="1049" depart="524.50" from="154844463#0" to="80915867#2"/>
    <trip id="1050" depart="525.00" from="22907738#10" to="36917807#1"/>
    <trip id="1051" depart="525.50" from="-134640698#2" to="-111981879#3"/>
    <trip id="1052" depart="526.00" from="58413965#2" to="833993643#0"/>
    <trip id="1053" depart="526.50" from="372491631" to="44468712#33"/>
    <trip id="1054" depart="527.00" from="133165487#0" to="58780677#3"/>
    <trip id="1055" depart="527.50" from="-816876620" to="38228091#9"/>
    <trip id="1056" depart="528.00" from="-106615437#3" to="191206960#1"/>
    <trip id="1057" depart="528.50" from="1177239720#0" to="327375909"/>
    <trip id="1058" depart="529.00" from="37202320#2" to="324352207#6"/>
    <trip id="1059" depart="529.50" from="154500706#0" to="170566076#2"/>
    <trip id="1060" depart="530.00" from="-106255758#0" to="23575175#1"/>
    <trip id="1061" depart="530.50" from="-107426149#1" to="22956122#3"/>
    <trip id="1062" depart="531.00" from="1055983338#2" to="882042827#3"/>
    <trip id="1063" depart="531.50" from="-110531716#1" to="562077267#6"/>
    <trip id="1064" depart="532.00" from="37348281#0" to="552704373#2"/>
    <trip id="1065" depart="532.50" from="765105682#0" to="-22897703"/>
    <trip id="1066" depart="533.00" from="-197571749" to="-37761134#5"/>
    <trip id="1067" depart="533.50" from="-572748521#4" to="22908661#0"/>
    <trip id="1068" depart="534.00" from="535658884#0" to="107426168#1"/>
    <trip id="1069" depart="534.50" from="129305557#0" to="128039750#2"/>
    <trip id="1070" depart="535.00" from="132316382#4" to="25568849#0"/>
    <trip id="1071" depart="535.50" from="932418340#1" to="-839327616#8"/>
    <trip id="1072" depart="536.00" from="37631033#8" to="59712741#1"/>
    <trip id="1073" depart="536.50" from="368807876#7" to="646315024#0"/>
    <trip id="1074" depart="537.00" from="42045174#2" to="-183728839"/>
    <trip id="1075" depart="537.50" from="121952564#3" to="23683989#18"/>
    <trip id="1076" depart="538.00" from="-134155188#0" to="-105601667#0"/>
    <trip id="1077" depart="538.50" from="-43684741#4" to="185581507#2"/>
    <trip id="1078" depart="539.00" from="134417918#15" to="486666533#6"/>
    <trip id="1079" depart="539.50" from="234298685#1" to="646294502#4"/>
    <trip id="1080" depart="540.00" from="-196325888#3" to="22954833#11"/>
    <trip id="1081" depart="540.50" from="-127949021" to="-755179063#1"/>
    <trip id="1082" depart="541.00" from="635342379#2" to="727582094#0"/>
    <trip id="1083" depart="541.50" from="149862033#0" to="-122258528#7"/>
    <trip id="1084" depart="542.00" from="-154484171#5" to="81563075#1"/>
    <trip id="1085" depart="542.50" from="749296447" to="254093319"/>
    <trip id="1086" depart="543.00" from="-116611298#4" to="816387299#1"/>
    <trip id="1087" depart="543.50" from="1109766696#1" to="873278978#1"/>
    <trip id="1088" depart="544.00" from="257357078#11" to="43205235#2"/>
    <trip id="1089" depart="544.50" from="37985910#0" to="133266924"/>
    <trip id="1090" depart="545.00" from="-154716225#1" to="-39831540#10"/>
    <trip id="1091" depart="545.50" from="-83710621" to="58414208#6"/>
    <trip id="1092" depart="546.00" from="127737006#1" to="756859271#0"/>
    <trip id="1093" depart="546.50" from="111801779#0" to="43661334#3"/>
    <trip id="1094" depart="547.00" from="-37468446#5" to="925550472#0"/>
    <trip id="1095" depart="547.50" from="38279264" to="185594234#1"/>
    <trip id="1096" depart="548.00" from="881905842#2" to="-132316382#6"/>
    <trip id="1097" depart="548.50" from="134460789#0" to="58768055#20"/>
    <trip id="1098" depart="549.00" from="111995488#5" to="454001361#2"/>
    <trip id="1099" depart="549.50" from="858064349#0" to="133259881#2"/>
    <trip id="1100" depart="550.00" from="43836952#0" to="-111702128#4"/>
    <trip id="1101" depart="550.50" from="1055729989#0" to="946456581#1"/>
    <trip id="1102" depart="551.00" from="154986389#1" to="120649994#9"/>
    <trip id="1103" depart="551.50" from="8272336#1" to="138022926#0"/>
    <trip id="1104" depart="552.00" from="37468444#8" to="37464531#2"/>
    <trip id="1105" depart="552.50" from="-173047160" to="329093829#1"/>
    <trip id="1106" depart="553.00" from="486664926#1" to="38323011#4"/>
    <trip id="1107" depart="553.50" from="-163979756#3" to="-38027668#3"/>
    <trip id="1108" depart="554.00" from="37981427#7" to="36812654#7"/>
    <trip id="1109" depart="554.50" from="39971282#1" to="111995455#0"/>
    <trip id="1110" depart="555.00" from="-23463862" to="-104148308#0"/>
    <trip id="1111" depart="555.50" from="110678682#10" to="121952583#8"/>
    <trip id="1112" depart="556.00" from="104675336#0" to="-329301856#1"/>
    <trip id="1113" depart="556.50" from="-559745891" to="149190771#3"/>
    <trip id="1114" depart="557.00" from="23054660#1" to="134109952#0"/>
    <trip id="1115" depart="557.50" from="-112002478#3" to="1186075027"/>
    <trip id="1116" depart="558.00" from="-191381259" to="29180289#0"/>
    <trip id="1117" depart="558.50" from="111581104#0" to="132316369"/>
    <trip id="1118" depart="559.00" from="107426175#2" to="132319215#3"/>
    <trip id="1119" depart="559.50" from="-172409586#1" to="757911747#1"/>
    <trip id="1120" depart="560.00" from="757534983#0" to="884054123"/>
    <trip id="1121" depart="560.50" from="243127219#2" to="-40870792"/>
    <trip id="1122" depart="561.00" from="122258521#2" to="-36875183#1"/>
    <trip id="1123" depart="561.50" from="1095219590#0" to="173211625#0"/>
    <trip id="1124" depart="562.00" from="-135860932#2" to="144874008#2"/>
    <trip id="1125" depart="562.50" from="133855813#0" to="167457302"/>
    <trip id="1126" depart="563.00" from="-154716225#1" to="105283539"/>
    <trip id="1127" depart="563.50" from="-875435450#2" to="353164584"/>
    <trip id="1128" depart="564.00" from="26982286#1" to="-58780677#0"/>
    <trip id="1129" depart="564.50" from="-23490352#2" to="111649306#7"/>
    <trip id="1130" depart="565.00" from="83709549#5" to="1135142887#1"/>
    <trip id="1131" depart="565.50" from="306423366#0" to="551896092#0"/>
    <trip id="1132" depart="566.00" from="1117123169#0" to="1137219924"/>
    <trip id="1133" depart="566.50" from="543492893#0" to="649706891"/>
    <trip id="1134" depart="567.00" from="881905842#0" to="-356857809#2"/>
    <trip id="1135" depart="567.50" from="111504819#0" to="836500946#1"/>
    <trip id="1136" depart="568.00" from="-59712409#6" to="111859668#1"/>
    <trip id="1137" depart="568.50" from="874650462#1" to="876531525#0"/>
    <trip id="1138" depart="569.00" from="107426168#4" to="37973571#5"/>
    <trip id="1139" depart="569.50" from="154986394#14" to="264213406#2"/>
    <trip id="1140" depart="570.00" from="-85426929#1" to="129252320#7"/>
    <trip id="1141" depart="570.50" from="551875154#0" to="133011266#0"/>
    <trip id="1142" depart="571.00" from="-257027156#2" to="254417917#2"/>
    <trip id="1143" depart="571.50" from="26540081#5" to="23182423#4"/>
    <trip id="1144" depart="572.00" from="375045488#11" to="23463811#1"/>
    <trip id="1145" depart="572.50" from="847569412" to="154484171#1"/>
    <trip id="1146" depart="573.00" from="379514452" to="148961536#0"/>
    <trip id="1147" depart="573.50" from="107426168#0" to="379514449"/>
    <trip id="1148" depart="574.00" from="552704373#1" to="499694885#2"/>
    <trip id="1149" depart="574.50" from="132419488" to="185581500#0"/>
    <trip id="1150" depart="575.00" from="327426871#0" to="101272426#8"/>
    <trip id="1151" depart="575.50" from="36936416#12" to="39231082#0"/>
    <trip id="1152" depart="576.00" from="47289660#0" to="-149116229"/>
    <trip id="1153" depart="576.50" from="932946817" to="160601728#1"/>
    <trip id="1154" depart="577.00" from="130443647#7" to="191213707"/>
    <trip id="1155" depart="577.50" from="80451876#9" to="37908671"/>
    <trip id="1156" depart="578.00" from="22908661#2" to="49047582#0"/>
    <trip id="1157" depart="578.50" from="1149100647#1" to="756569653#3"/>
    <trip id="1158" depart="579.00" from="222769029#2" to="368807875#16"/>
    <trip id="1159" depart="579.50" from="-173047158#0" to="454001361#1"/>
    <trip id="1160" depart="580.00" from="36932291#1" to="120517721"/>
    <trip id="1161" depart="580.50" from="36773697#4" to="-1177239723#0"/>
    <trip id="1162" depart="581.00" from="895346658" to="37739016#1"/>
    <trip id="1163" depart="581.50" from="130443636#10" to="43205336#4"/>
    <trip id="1164" depart="582.00" from="875445772#7" to="135860931#6"/>
    <trip id="1165" depart="582.50" from="-107028581#2" to="106410345#0"/>
    <trip id="1166" depart="583.00" from="173047157#0" to="220847826#4"/>
    <trip id="1167" depart="583.50" from="254417917#1" to="26293224#1"/>
    <trip id="1168" depart="584.00" from="135555665#1" to="132527898#1"/>
    <trip id="1169" depart="584.50" from="43685239#0" to="28107136#0"/>
    <trip id="1170" depart="585.00" from="164972161#0" to="116810533#0"/>
    <trip id="1171" depart="585.50" from="-111863117#3" to="-209264725"/>
    <trip id="1172" depart="586.00" from="133259886#4" to="873283811#1"/>
    <trip id="1173" depart="586.50" from="-257538838#0" to="8272356#0"/>
    <trip id="1174" depart="587.00" from="-376503487#4" to="111801811#2"/>
    <trip id="1175" depart="587.50" from="145954707#0" to="-678628384#6"/>
    <trip id="1176" depart="588.00" from="154500693#1" to="160584976"/>
    <trip id="1178" depart="589.00" from="111262067#1" to="1115285029"/>
    <trip id="1179" depart="589.50" from="50339385#11" to="-239720651#5"/>
    <trip id="1180" depart="590.00" from="58768055#1" to="371215546"/>
    <trip id="1181" depart="590.50" from="37464529#2" to="-39977259#0"/>
    <trip id="1182" depart="591.00" from="900277729#0" to="1015878042#3"/>
    <trip id="1183" depart="591.50" from="-44580449" to="-39671240#0"/>
    <trip id="1184" depart="592.00" from="23171475#0" to="864658909#3"/>
    <trip id="1185" depart="592.50" from="-817232516#1" to="133868181#5"/>
    <trip id="1186" depart="593.00" from="-524463976#4" to="36916541#18"/>
    <trip id="1187" depart="593.50" from="134155188#9" to="-1116355284#0"/>
    <trip id="1188" depart="594.00" from="293287047#7" to="-594306218#1"/>
    <trip id="1189" depart="594.50" from="26540081#4" to="132364746#0"/>
    <trip id="1190" depart="595.00" from="37895373#4" to="-676847689#10"/>
    <trip id="1191" depart="595.50" from="40760621#2" to="559744473#3"/>
    <trip id="1192" depart="596.00" from="-135860931#13" to="-207858127"/>
    <trip id="1193" depart="596.50" from="6502123#7" to="-561062056#0"/>
    <trip id="1194" depart="597.00" from="111604728#0" to="150260120#1"/>
    <trip id="1195" depart="597.50" from="102273050#19" to="657572415#1"/>
    <trip id="1196" depart="598.00" from="201096134#0" to="36903944#1"/>
    <trip id="1197" depart="598.50" from="27648840#0" to="317403809#9"/>
    <trip id="1198" depart="599.00" from="257357078#11" to="1169193227"/>
    <trip id="1199" depart="599.50" from="58413955#2" to="325162773"/>
</routes>
